// Class: io/quarkus/runner/AutoFeature
//     Access =  public synthetic
//     Extends: java/lang/Object
//     Implements:
//         org/graalvm/nativeimage/Feature

// DO NOT MODIFY.  This is not actually a source file; it is a textual representation of generated code.
// Use only for debugging purposes.

// Auto-generated constructor
// Access: public
Method <init> : V
(
    // (no arguments)
) {
    ALOAD 0
    // Method descriptor: ()V
    INVOKESPECIAL java/lang/Object#<init>
    RETURN
    
}

// Access: private static
Method registerClass8 : V
(
    // (no arguments)
) {
    ** label1
    ** label2
    LDC (String) "com.github.wglanzer.common.EventSerializer"
    // Method descriptor: (Ljava/lang/String;)Ljava/lang/Class;
    INVOKESTATIC java/lang/Class#forName
    ASTORE 0
    ALOAD 0
    // Method descriptor: ()[Ljava/lang/reflect/Constructor;
    INVOKEVIRTUAL java/lang/Class#getDeclaredConstructors
    ASTORE 2
    ALOAD 0
    // Method descriptor: ()[Ljava/lang/reflect/Method;
    INVOKEVIRTUAL java/lang/Class#getDeclaredMethods
    ASTORE 3
    ALOAD 0
    // Method descriptor: ()[Ljava/lang/reflect/Field;
    INVOKEVIRTUAL java/lang/Class#getDeclaredFields
    ASTORE 4
    LDC (Integer) 1
    ANEWARRAY java/lang/Class
    ASTORE 1
    ALOAD 1
    LDC (Integer) 0
    ALOAD 0
    AASTORE
    ALOAD 1
    // Method descriptor: ([Ljava/lang/Class;)V
    INVOKESTATIC org/graalvm/nativeimage/RuntimeReflection#register
    ALOAD 2
    CHECKCAST [Ljava/lang/reflect/Executable;
    // Method descriptor: ([Ljava/lang/reflect/Executable;)V
    INVOKESTATIC org/graalvm/nativeimage/RuntimeReflection#register
    ALOAD 3
    CHECKCAST [Ljava/lang/reflect/Executable;
    // Method descriptor: ([Ljava/lang/reflect/Executable;)V
    INVOKESTATIC org/graalvm/nativeimage/RuntimeReflection#register
    LDC (Boolean) false
    ALOAD 4
    // Method descriptor: (Z[Ljava/lang/reflect/Field;)V
    INVOKESTATIC org/graalvm/nativeimage/RuntimeReflection#register
    ** label3
    GOTO label4
    ** label5
    POP
    ** label6
    GOTO label4
    // Try from label2 to label3
    // Catch java/lang/Throwable by going to label5
    ** label4
    RETURN
    ** label7
    
}

// Access: private static
Method registerClass9 : V
(
    // (no arguments)
) {
    ** label1
    ** label2
    LDC (String) "com.github.wglanzer.common.EventDeserializer"
    // Method descriptor: (Ljava/lang/String;)Ljava/lang/Class;
    INVOKESTATIC java/lang/Class#forName
    ASTORE 0
    ALOAD 0
    // Method descriptor: ()[Ljava/lang/reflect/Constructor;
    INVOKEVIRTUAL java/lang/Class#getDeclaredConstructors
    ASTORE 2
    ALOAD 0
    // Method descriptor: ()[Ljava/lang/reflect/Method;
    INVOKEVIRTUAL java/lang/Class#getDeclaredMethods
    ASTORE 3
    ALOAD 0
    // Method descriptor: ()[Ljava/lang/reflect/Field;
    INVOKEVIRTUAL java/lang/Class#getDeclaredFields
    ASTORE 4
    LDC (Integer) 1
    ANEWARRAY java/lang/Class
    ASTORE 1
    ALOAD 1
    LDC (Integer) 0
    ALOAD 0
    AASTORE
    ALOAD 1
    // Method descriptor: ([Ljava/lang/Class;)V
    INVOKESTATIC org/graalvm/nativeimage/RuntimeReflection#register
    ALOAD 2
    CHECKCAST [Ljava/lang/reflect/Executable;
    // Method descriptor: ([Ljava/lang/reflect/Executable;)V
    INVOKESTATIC org/graalvm/nativeimage/RuntimeReflection#register
    ALOAD 3
    CHECKCAST [Ljava/lang/reflect/Executable;
    // Method descriptor: ([Ljava/lang/reflect/Executable;)V
    INVOKESTATIC org/graalvm/nativeimage/RuntimeReflection#register
    LDC (Boolean) false
    ALOAD 4
    // Method descriptor: (Z[Ljava/lang/reflect/Field;)V
    INVOKESTATIC org/graalvm/nativeimage/RuntimeReflection#register
    ** label3
    GOTO label4
    ** label5
    POP
    ** label6
    GOTO label4
    // Try from label2 to label3
    // Catch java/lang/Throwable by going to label5
    ** label4
    RETURN
    ** label7
    
}

// Access: private static
Method registerClass6 : V
(
    // (no arguments)
) {
    ** label1
    ** label2
    LDC (String) "java.util.TreeMap"
    // Method descriptor: (Ljava/lang/String;)Ljava/lang/Class;
    INVOKESTATIC java/lang/Class#forName
    ASTORE 0
    ALOAD 0
    // Method descriptor: ()[Ljava/lang/reflect/Constructor;
    INVOKEVIRTUAL java/lang/Class#getDeclaredConstructors
    ASTORE 2
    ALOAD 0
    // Method descriptor: ()[Ljava/lang/reflect/Method;
    INVOKEVIRTUAL java/lang/Class#getDeclaredMethods
    POP
    ALOAD 0
    // Method descriptor: ()[Ljava/lang/reflect/Field;
    INVOKEVIRTUAL java/lang/Class#getDeclaredFields
    POP
    LDC (Integer) 1
    ANEWARRAY java/lang/Class
    ASTORE 1
    ALOAD 1
    LDC (Integer) 0
    ALOAD 0
    AASTORE
    ALOAD 1
    // Method descriptor: ([Ljava/lang/Class;)V
    INVOKESTATIC org/graalvm/nativeimage/RuntimeReflection#register
    ALOAD 2
    CHECKCAST [Ljava/lang/reflect/Executable;
    // Method descriptor: ([Ljava/lang/reflect/Executable;)V
    INVOKESTATIC org/graalvm/nativeimage/RuntimeReflection#register
    ** label3
    GOTO label4
    ** label5
    POP
    ** label6
    GOTO label4
    // Try from label2 to label3
    // Catch java/lang/Throwable by going to label5
    ** label4
    RETURN
    ** label7
    
}

// Access: private static
Method registerClass7 : V
(
    // (no arguments)
) {
    ** label1
    ** label2
    LDC (String) "java.util.TreeSet"
    // Method descriptor: (Ljava/lang/String;)Ljava/lang/Class;
    INVOKESTATIC java/lang/Class#forName
    ASTORE 0
    ALOAD 0
    // Method descriptor: ()[Ljava/lang/reflect/Constructor;
    INVOKEVIRTUAL java/lang/Class#getDeclaredConstructors
    ASTORE 2
    ALOAD 0
    // Method descriptor: ()[Ljava/lang/reflect/Method;
    INVOKEVIRTUAL java/lang/Class#getDeclaredMethods
    POP
    ALOAD 0
    // Method descriptor: ()[Ljava/lang/reflect/Field;
    INVOKEVIRTUAL java/lang/Class#getDeclaredFields
    POP
    LDC (Integer) 1
    ANEWARRAY java/lang/Class
    ASTORE 1
    ALOAD 1
    LDC (Integer) 0
    ALOAD 0
    AASTORE
    ALOAD 1
    // Method descriptor: ([Ljava/lang/Class;)V
    INVOKESTATIC org/graalvm/nativeimage/RuntimeReflection#register
    ALOAD 2
    CHECKCAST [Ljava/lang/reflect/Executable;
    // Method descriptor: ([Ljava/lang/reflect/Executable;)V
    INVOKESTATIC org/graalvm/nativeimage/RuntimeReflection#register
    ** label3
    GOTO label4
    ** label5
    POP
    ** label6
    GOTO label4
    // Try from label2 to label3
    // Catch java/lang/Throwable by going to label5
    ** label4
    RETURN
    ** label7
    
}

// Access: private static
Method registerClass0 : V
(
    // (no arguments)
) {
    ** label1
    ** label2
    LDC (String) "java.util.ArrayList"
    // Method descriptor: (Ljava/lang/String;)Ljava/lang/Class;
    INVOKESTATIC java/lang/Class#forName
    ASTORE 0
    ALOAD 0
    // Method descriptor: ()[Ljava/lang/reflect/Constructor;
    INVOKEVIRTUAL java/lang/Class#getDeclaredConstructors
    ASTORE 2
    ALOAD 0
    // Method descriptor: ()[Ljava/lang/reflect/Method;
    INVOKEVIRTUAL java/lang/Class#getDeclaredMethods
    POP
    ALOAD 0
    // Method descriptor: ()[Ljava/lang/reflect/Field;
    INVOKEVIRTUAL java/lang/Class#getDeclaredFields
    POP
    LDC (Integer) 1
    ANEWARRAY java/lang/Class
    ASTORE 1
    ALOAD 1
    LDC (Integer) 0
    ALOAD 0
    AASTORE
    ALOAD 1
    // Method descriptor: ([Ljava/lang/Class;)V
    INVOKESTATIC org/graalvm/nativeimage/RuntimeReflection#register
    ALOAD 2
    CHECKCAST [Ljava/lang/reflect/Executable;
    // Method descriptor: ([Ljava/lang/reflect/Executable;)V
    INVOKESTATIC org/graalvm/nativeimage/RuntimeReflection#register
    ** label3
    GOTO label4
    ** label5
    POP
    ** label6
    GOTO label4
    // Try from label2 to label3
    // Catch java/lang/Throwable by going to label5
    ** label4
    RETURN
    ** label7
    
}

// Access: private static
Method registerClass1 : V
(
    // (no arguments)
) {
    ** label1
    ** label2
    LDC (String) "java.util.HashMap"
    // Method descriptor: (Ljava/lang/String;)Ljava/lang/Class;
    INVOKESTATIC java/lang/Class#forName
    ASTORE 0
    ALOAD 0
    // Method descriptor: ()[Ljava/lang/reflect/Constructor;
    INVOKEVIRTUAL java/lang/Class#getDeclaredConstructors
    ASTORE 2
    ALOAD 0
    // Method descriptor: ()[Ljava/lang/reflect/Method;
    INVOKEVIRTUAL java/lang/Class#getDeclaredMethods
    POP
    ALOAD 0
    // Method descriptor: ()[Ljava/lang/reflect/Field;
    INVOKEVIRTUAL java/lang/Class#getDeclaredFields
    POP
    LDC (Integer) 1
    ANEWARRAY java/lang/Class
    ASTORE 1
    ALOAD 1
    LDC (Integer) 0
    ALOAD 0
    AASTORE
    ALOAD 1
    // Method descriptor: ([Ljava/lang/Class;)V
    INVOKESTATIC org/graalvm/nativeimage/RuntimeReflection#register
    ALOAD 2
    CHECKCAST [Ljava/lang/reflect/Executable;
    // Method descriptor: ([Ljava/lang/reflect/Executable;)V
    INVOKESTATIC org/graalvm/nativeimage/RuntimeReflection#register
    ** label3
    GOTO label4
    ** label5
    POP
    ** label6
    GOTO label4
    // Try from label2 to label3
    // Catch java/lang/Throwable by going to label5
    ** label4
    RETURN
    ** label7
    
}

// Access: public
Method beforeAnalysis : V
(
    arg 1 = Lorg/graalvm/nativeimage/Feature$BeforeAnalysisAccess;
) {
    ** label1
    ** label2
    LDC (Integer) 1
    ANEWARRAY java/lang/Class
    ASTORE 4
    LDC (Type) Lio/quarkus/runner/AutoFeature;
    // Method descriptor: ()Ljava/lang/ClassLoader;
    INVOKEVIRTUAL java/lang/Class#getClassLoader
    ASTORE 2
    ** label3
    LDC (String) "org.jboss.logmanager.formatters.TrueColorHolder"
    LDC (Boolean) false
    ALOAD 2
    // Method descriptor: (Ljava/lang/String;ZLjava/lang/ClassLoader;)Ljava/lang/Class;
    INVOKESTATIC java/lang/Class#forName
    ASTORE 3
    ALOAD 4
    LDC (Integer) 0
    ALOAD 3
    AASTORE
    ALOAD 4
    // Method descriptor: ([Ljava/lang/Class;)V
    INVOKESTATIC org/graalvm/nativeimage/RuntimeClassInitialization#delayClassInitialization
    ** label4
    GOTO label5
    ** label6
    ASTORE 5
    ALOAD 5
    // Method descriptor: ()V
    INVOKEVIRTUAL java/lang/Throwable#printStackTrace
    ** label7
    GOTO label5
    // Try from label3 to label4
    // Catch java/lang/Throwable by going to label6
    ** label5
    ** label8
    LDC (String) "io.quarkus.runtime.ExecutorTemplate"
    LDC (Boolean) false
    ALOAD 2
    // Method descriptor: (Ljava/lang/String;ZLjava/lang/ClassLoader;)Ljava/lang/Class;
    INVOKESTATIC java/lang/Class#forName
    ASTORE 6
    ALOAD 4
    LDC (Integer) 0
    ALOAD 6
    AASTORE
    ALOAD 4
    // Method descriptor: ([Ljava/lang/Class;)V
    INVOKESTATIC org/graalvm/nativeimage/RuntimeClassInitialization#delayClassInitialization
    ** label9
    GOTO label10
    ** label11
    ASTORE 7
    ALOAD 7
    // Method descriptor: ()V
    INVOKEVIRTUAL java/lang/Throwable#printStackTrace
    ** label12
    GOTO label10
    // Try from label8 to label9
    // Catch java/lang/Throwable by going to label11
    ** label10
    ** label13
    LDC (String) "io.quarkus.runtime.generated.RunTimeConfig"
    LDC (Boolean) false
    ALOAD 2
    // Method descriptor: (Ljava/lang/String;ZLjava/lang/ClassLoader;)Ljava/lang/Class;
    INVOKESTATIC java/lang/Class#forName
    ASTORE 8
    ALOAD 4
    LDC (Integer) 0
    ALOAD 8
    AASTORE
    ALOAD 4
    // Method descriptor: ([Ljava/lang/Class;)V
    INVOKESTATIC org/graalvm/nativeimage/RuntimeClassInitialization#delayClassInitialization
    ** label14
    GOTO label15
    ** label16
    ASTORE 9
    ALOAD 9
    // Method descriptor: ()V
    INVOKEVIRTUAL java/lang/Throwable#printStackTrace
    ** label17
    GOTO label15
    // Try from label13 to label14
    // Catch java/lang/Throwable by going to label16
    ** label15
    LDC (Integer) 1
    ANEWARRAY java/lang/Class
    POP
    LDC (Type) Lio/quarkus/runner/AutoFeature;
    // Method descriptor: ()Ljava/lang/ClassLoader;
    INVOKEVIRTUAL java/lang/Class#getClassLoader
    POP
    LDC (String) "META-INF/build-config.properties"
    // Method descriptor: (Ljava/lang/String;)V
    INVOKESTATIC io/quarkus/runtime/ResourceHelper#registerResources
    LDC (String) "META-INF/quarkus-default-config.properties"
    // Method descriptor: (Ljava/lang/String;)V
    INVOKESTATIC io/quarkus/runtime/ResourceHelper#registerResources
    LDC (String) "META-INF/services/org.jboss.logmanager.EmbeddedConfigurator"
    // Method descriptor: (Ljava/lang/String;)V
    INVOKESTATIC io/quarkus/runtime/ResourceHelper#registerResources
    // Method descriptor: ()V
    INVOKESTATIC io/quarkus/runner/AutoFeature#registerClass0
    // Method descriptor: ()V
    INVOKESTATIC io/quarkus/runner/AutoFeature#registerClass1
    // Method descriptor: ()V
    INVOKESTATIC io/quarkus/runner/AutoFeature#registerClass2
    // Method descriptor: ()V
    INVOKESTATIC io/quarkus/runner/AutoFeature#registerClass3
    // Method descriptor: ()V
    INVOKESTATIC io/quarkus/runner/AutoFeature#registerClass4
    // Method descriptor: ()V
    INVOKESTATIC io/quarkus/runner/AutoFeature#registerClass5
    // Method descriptor: ()V
    INVOKESTATIC io/quarkus/runner/AutoFeature#registerClass6
    // Method descriptor: ()V
    INVOKESTATIC io/quarkus/runner/AutoFeature#registerClass7
    // Method descriptor: ()V
    INVOKESTATIC io/quarkus/runner/AutoFeature#registerClass8
    // Method descriptor: ()V
    INVOKESTATIC io/quarkus/runner/AutoFeature#registerClass9
    // Method descriptor: ()V
    INVOKESTATIC io/quarkus/runner/AutoFeature#registerClass10
    ** label18
    GOTO label19
    ** label20
    ASTORE 10
    ALOAD 10
    // Method descriptor: ()V
    INVOKEVIRTUAL java/lang/Throwable#printStackTrace
    ** label21
    GOTO label19
    // Try from label2 to label18
    // Catch java/lang/Throwable by going to label20
    ** label19
    RETURN
    ** label22
    
}

// Access: private static
Method registerClass4 : V
(
    // (no arguments)
) {
    ** label1
    ** label2
    LDC (String) "java.util.LinkedHashMap"
    // Method descriptor: (Ljava/lang/String;)Ljava/lang/Class;
    INVOKESTATIC java/lang/Class#forName
    ASTORE 0
    ALOAD 0
    // Method descriptor: ()[Ljava/lang/reflect/Constructor;
    INVOKEVIRTUAL java/lang/Class#getDeclaredConstructors
    ASTORE 2
    ALOAD 0
    // Method descriptor: ()[Ljava/lang/reflect/Method;
    INVOKEVIRTUAL java/lang/Class#getDeclaredMethods
    POP
    ALOAD 0
    // Method descriptor: ()[Ljava/lang/reflect/Field;
    INVOKEVIRTUAL java/lang/Class#getDeclaredFields
    POP
    LDC (Integer) 1
    ANEWARRAY java/lang/Class
    ASTORE 1
    ALOAD 1
    LDC (Integer) 0
    ALOAD 0
    AASTORE
    ALOAD 1
    // Method descriptor: ([Ljava/lang/Class;)V
    INVOKESTATIC org/graalvm/nativeimage/RuntimeReflection#register
    ALOAD 2
    CHECKCAST [Ljava/lang/reflect/Executable;
    // Method descriptor: ([Ljava/lang/reflect/Executable;)V
    INVOKESTATIC org/graalvm/nativeimage/RuntimeReflection#register
    ** label3
    GOTO label4
    ** label5
    POP
    ** label6
    GOTO label4
    // Try from label2 to label3
    // Catch java/lang/Throwable by going to label5
    ** label4
    RETURN
    ** label7
    
}

// Access: private static
Method registerClass10 : V
(
    // (no arguments)
) {
    ** label1
    ** label2
    LDC (String) "io.quarkus.runtime.logging.InitialConfigurator"
    // Method descriptor: (Ljava/lang/String;)Ljava/lang/Class;
    INVOKESTATIC java/lang/Class#forName
    ASTORE 0
    ALOAD 0
    // Method descriptor: ()[Ljava/lang/reflect/Constructor;
    INVOKEVIRTUAL java/lang/Class#getDeclaredConstructors
    ASTORE 2
    ALOAD 0
    // Method descriptor: ()[Ljava/lang/reflect/Method;
    INVOKEVIRTUAL java/lang/Class#getDeclaredMethods
    POP
    ALOAD 0
    // Method descriptor: ()[Ljava/lang/reflect/Field;
    INVOKEVIRTUAL java/lang/Class#getDeclaredFields
    POP
    LDC (Integer) 1
    ANEWARRAY java/lang/Class
    ASTORE 1
    ALOAD 1
    LDC (Integer) 0
    ALOAD 0
    AASTORE
    ALOAD 1
    // Method descriptor: ([Ljava/lang/Class;)V
    INVOKESTATIC org/graalvm/nativeimage/RuntimeReflection#register
    ALOAD 2
    CHECKCAST [Ljava/lang/reflect/Executable;
    // Method descriptor: ([Ljava/lang/reflect/Executable;)V
    INVOKESTATIC org/graalvm/nativeimage/RuntimeReflection#register
    ** label3
    GOTO label4
    ** label5
    POP
    ** label6
    GOTO label4
    // Try from label2 to label3
    // Catch java/lang/Throwable by going to label5
    ** label4
    RETURN
    ** label7
    
}

// Access: private static
Method registerClass5 : V
(
    // (no arguments)
) {
    ** label1
    ** label2
    LDC (String) "java.util.LinkedHashSet"
    // Method descriptor: (Ljava/lang/String;)Ljava/lang/Class;
    INVOKESTATIC java/lang/Class#forName
    ASTORE 0
    ALOAD 0
    // Method descriptor: ()[Ljava/lang/reflect/Constructor;
    INVOKEVIRTUAL java/lang/Class#getDeclaredConstructors
    ASTORE 2
    ALOAD 0
    // Method descriptor: ()[Ljava/lang/reflect/Method;
    INVOKEVIRTUAL java/lang/Class#getDeclaredMethods
    POP
    ALOAD 0
    // Method descriptor: ()[Ljava/lang/reflect/Field;
    INVOKEVIRTUAL java/lang/Class#getDeclaredFields
    POP
    LDC (Integer) 1
    ANEWARRAY java/lang/Class
    ASTORE 1
    ALOAD 1
    LDC (Integer) 0
    ALOAD 0
    AASTORE
    ALOAD 1
    // Method descriptor: ([Ljava/lang/Class;)V
    INVOKESTATIC org/graalvm/nativeimage/RuntimeReflection#register
    ALOAD 2
    CHECKCAST [Ljava/lang/reflect/Executable;
    // Method descriptor: ([Ljava/lang/reflect/Executable;)V
    INVOKESTATIC org/graalvm/nativeimage/RuntimeReflection#register
    ** label3
    GOTO label4
    ** label5
    POP
    ** label6
    GOTO label4
    // Try from label2 to label3
    // Catch java/lang/Throwable by going to label5
    ** label4
    RETURN
    ** label7
    
}

// Access: private static
Method registerClass2 : V
(
    // (no arguments)
) {
    ** label1
    ** label2
    LDC (String) "java.util.HashSet"
    // Method descriptor: (Ljava/lang/String;)Ljava/lang/Class;
    INVOKESTATIC java/lang/Class#forName
    ASTORE 0
    ALOAD 0
    // Method descriptor: ()[Ljava/lang/reflect/Constructor;
    INVOKEVIRTUAL java/lang/Class#getDeclaredConstructors
    ASTORE 2
    ALOAD 0
    // Method descriptor: ()[Ljava/lang/reflect/Method;
    INVOKEVIRTUAL java/lang/Class#getDeclaredMethods
    POP
    ALOAD 0
    // Method descriptor: ()[Ljava/lang/reflect/Field;
    INVOKEVIRTUAL java/lang/Class#getDeclaredFields
    POP
    LDC (Integer) 1
    ANEWARRAY java/lang/Class
    ASTORE 1
    ALOAD 1
    LDC (Integer) 0
    ALOAD 0
    AASTORE
    ALOAD 1
    // Method descriptor: ([Ljava/lang/Class;)V
    INVOKESTATIC org/graalvm/nativeimage/RuntimeReflection#register
    ALOAD 2
    CHECKCAST [Ljava/lang/reflect/Executable;
    // Method descriptor: ([Ljava/lang/reflect/Executable;)V
    INVOKESTATIC org/graalvm/nativeimage/RuntimeReflection#register
    ** label3
    GOTO label4
    ** label5
    POP
    ** label6
    GOTO label4
    // Try from label2 to label3
    // Catch java/lang/Throwable by going to label5
    ** label4
    RETURN
    ** label7
    
}

// Access: private static
Method registerClass3 : V
(
    // (no arguments)
) {
    ** label1
    ** label2
    LDC (String) "java.util.LinkedList"
    // Method descriptor: (Ljava/lang/String;)Ljava/lang/Class;
    INVOKESTATIC java/lang/Class#forName
    ASTORE 0
    ALOAD 0
    // Method descriptor: ()[Ljava/lang/reflect/Constructor;
    INVOKEVIRTUAL java/lang/Class#getDeclaredConstructors
    ASTORE 2
    ALOAD 0
    // Method descriptor: ()[Ljava/lang/reflect/Method;
    INVOKEVIRTUAL java/lang/Class#getDeclaredMethods
    POP
    ALOAD 0
    // Method descriptor: ()[Ljava/lang/reflect/Field;
    INVOKEVIRTUAL java/lang/Class#getDeclaredFields
    POP
    LDC (Integer) 1
    ANEWARRAY java/lang/Class
    ASTORE 1
    ALOAD 1
    LDC (Integer) 0
    ALOAD 0
    AASTORE
    ALOAD 1
    // Method descriptor: ([Ljava/lang/Class;)V
    INVOKESTATIC org/graalvm/nativeimage/RuntimeReflection#register
    ALOAD 2
    CHECKCAST [Ljava/lang/reflect/Executable;
    // Method descriptor: ([Ljava/lang/reflect/Executable;)V
    INVOKESTATIC org/graalvm/nativeimage/RuntimeReflection#register
    ** label3
    GOTO label4
    ** label5
    POP
    ** label6
    GOTO label4
    // Try from label2 to label3
    // Catch java/lang/Throwable by going to label5
    ** label4
    RETURN
    ** label7
    
}

